{
  "sync_id": "sync_20260122_210401",
  "earliest_start": "2025-11-29T22:50:00",
  "latest_end": "2025-11-30T00:33:16.517958",
  "total_duration_seconds": 6196.517958,
  "total_duration_formatted": "1:43:16",
  "videos_count": 49,
  "videos": [
    {
      "filename": "EdwardRuiz_202511292250_312-0.mp4",
      "path": "private-core-barber-cam\\.bwc\\25-41706 Barber, Devon\\EdwardRuiz_202511292250_312-0.mp4",
      "officer": "EdwardRuiz",
      "camera_id": "312-0",
      "recording_start": "2025-11-29T22:50:00",
      "duration_seconds": 3135.473167,
      "duration_formatted": "0:52:15",
      "resolution": "1280x720",
      "fps": 30.0,
      "codec": "h264",
      "file_size_mb": 1890.6591329574585
    },
    {
      "filename": "EdwardRuiz_202511292250_312-0.mp4",
      "path": "private-core-barber-cam\\.bwc\\atl-l-003252-25\\officer_Ruiz\\EdwardRuiz_202511292250_312-0.mp4",
      "officer": "EdwardRuiz",
      "camera_id": "312-0",
      "recording_start": "2025-11-29T22:50:00",
      "duration_seconds": 3135.473167,
      "duration_formatted": "0:52:15",
      "resolution": "1280x720",
      "fps": 30.0,
      "codec": "h264",
      "file_size_mb": 1890.6591329574585
    },
    {
      "filename": "EdwardRuiz_202511292251_BWL7139078-0.mp4",
      "path": "private-core-barber-cam\\.bwc\\25-41706 Barber, Devon\\EdwardRuiz_202511292251_BWL7139078-0.mp4",
      "officer": "EdwardRuiz",
      "camera_id": "BWL7139078-0",
      "recording_start": "2025-11-29T22:51:00",
      "duration_seconds": 1442.005313,
      "duration_formatted": "0:24:02",
      "resolution": "1920x1080",
      "fps": 30.0,
      "codec": "h264",
      "file_size_mb": 1720.1305093765259
    },
    {
      "filename": "EdwardRuiz_202511292251_BWL7139078-0.mp4",
      "path": "private-core-barber-cam\\.bwc\\atl-l-003252-25\\officer_Ruiz\\EdwardRuiz_202511292251_BWL7139078-0.mp4",
      "officer": "EdwardRuiz",
      "camera_id": "BWL7139078-0",
      "recording_start": "2025-11-29T22:51:00",
      "duration_seconds": 1442.005313,
      "duration_formatted": "0:24:02",
      "resolution": "1920x1080",
      "fps": 30.0,
      "codec": "h264",
      "file_size_mb": 1720.1305093765259
    },
    {
      "filename": "BryanMerritt_202511292256_311-0.mp4",
      "path": "private-core-barber-cam\\.bwc\\25-41706 Barber, Devon\\BryanMerritt_202511292256_311-0.mp4",
      "officer": "BryanMerritt",
      "camera_id": "311-0",
      "recording_start": "2025-11-29T22:56:00",
      "duration_seconds": 1133.009208,
      "duration_formatted": "0:18:53",
      "resolution": "1280x720",
      "fps": 30.0,
      "codec": "h264",
      "file_size_mb": 683.8683681488037
    },
    {
      "filename": "BryanMerritt_202511292256_311-0.mp4",
      "path": "private-core-barber-cam\\.bwc\\atl-l-003252-25\\officer_Merritt\\BryanMerritt_202511292256_311-0.mp4",
      "officer": "BryanMerritt",
      "camera_id": "311-0",
      "recording_start": "2025-11-29T22:56:00",
      "duration_seconds": 1133.009208,
      "duration_formatted": "0:18:53",
      "resolution": "1280x720",
      "fps": 30.0,
      "codec": "h264",
      "file_size_mb": 683.8683681488037
    },
    {
      "filename": "BryanMerritt_202511292256_311-0.mp4",
      "path": "private-core-barber-cam\\_runs\\25-41706-barber-devon\\run_20260103_125038\\video_originals\\25-41706 Barber, Devon\\BryanMerritt_202511292256_311-0.mp4",
      "officer": "BryanMerritt",
      "camera_id": "311-0",
      "recording_start": "2025-11-29T22:56:00",
      "duration_seconds": 1133.009208,
      "duration_formatted": "0:18:53",
      "resolution": "1280x720",
      "fps": 30.0,
      "codec": "h264",
      "file_size_mb": 683.8683681488037
    },
    {
      "filename": "BryanMerritt_202511292257_BWL7137497-0.mp4",
      "path": "private-core-barber-cam\\.bwc\\25-41706 Barber, Devon\\BryanMerritt_202511292257_BWL7137497-0.mp4",
      "officer": "BryanMerritt",
      "camera_id": "BWL7137497-0",
      "recording_start": "2025-11-29T22:57:00",
      "duration_seconds": 1071.0,
      "duration_formatted": "0:17:51",
      "resolution": "1920x1080",
      "fps": 30.0,
      "codec": "h264",
      "file_size_mb": 1283.0219955444336
    },
    {
      "filename": "BryanMerritt_202511292257_BWL7137497-0.mp4",
      "path": "private-core-barber-cam\\.bwc\\atl-l-003252-25\\officer_Merritt\\BryanMerritt_202511292257_BWL7137497-0.mp4",
      "officer": "BryanMerritt",
      "camera_id": "BWL7137497-0",
      "recording_start": "2025-11-29T22:57:00",
      "duration_seconds": 1071.0,
      "duration_formatted": "0:17:51",
      "resolution": "1920x1080",
      "fps": 30.0,
      "codec": "h264",
      "file_size_mb": 1283.0219955444336
    },
    {
      "filename": "BryanMerritt_202511292257_BWL7137497-0.mp4",
      "path": "private-core-barber-cam\\_runs\\25-41706-barber-devon\\run_20260103_125038\\video_originals\\25-41706 Barber, Devon\\BryanMerritt_202511292257_BWL7137497-0.mp4",
      "officer": "BryanMerritt",
      "camera_id": "BWL7137497-0",
      "recording_start": "2025-11-29T22:57:00",
      "duration_seconds": 1071.0,
      "duration_formatted": "0:17:51",
      "resolution": "1920x1080",
      "fps": 30.0,
      "codec": "h264",
      "file_size_mb": 1283.0219955444336
    },
    {
      "filename": "RachelHare_202511292258_BWL7139108-0.mp4",
      "path": "private-core-barber-cam\\.bwc\\25-41706 Barber, Devon\\RachelHare_202511292258_BWL7139108-0.mp4",
      "officer": "RachelHare",
      "camera_id": "BWL7139108-0",
      "recording_start": "2025-11-29T22:58:00",
      "duration_seconds": 1510.0,
      "duration_formatted": "0:25:10",
      "resolution": "1920x1080",
      "fps": 30.0,
      "codec": "h264",
      "file_size_mb": 1807.5703172683716
    },
    {
      "filename": "RachelHare_202511292258_BWL7139108-0.mp4",
      "path": "private-core-barber-cam\\.bwc\\atl-l-003252-25\\officer_Hare\\RachelHare_202511292258_BWL7139108-0.mp4",
      "officer": "RachelHare",
      "camera_id": "BWL7139108-0",
      "recording_start": "2025-11-29T22:58:00",
      "duration_seconds": 1510.0,
      "duration_formatted": "0:25:10",
      "resolution": "1920x1080",
      "fps": 30.0,
      "codec": "h264",
      "file_size_mb": 1807.5703172683716
    },
    {
      "filename": "KyleMcknight_202511292310_310-0.mp4",
      "path": "private-core-barber-cam\\.bwc\\25-41706 Barber, Devon\\KyleMcknight_202511292310_310-0.mp4",
      "officer": "KyleMcknight",
      "camera_id": "310-0",
      "recording_start": "2025-11-29T23:10:00",
      "duration_seconds": 737.961708,
      "duration_formatted": "0:12:17",
      "resolution": "1280x720",
      "fps": 30.0,
      "codec": "h264",
      "file_size_mb": 444.9895992279053
    },
    {
      "filename": "KyleMcknight_202511292310_310-0.mp4",
      "path": "private-core-barber-cam\\.bwc\\atl-l-003252-25\\officer_Mcknight\\KyleMcknight_202511292310_310-0.mp4",
      "officer": "KyleMcknight",
      "camera_id": "310-0",
      "recording_start": "2025-11-29T23:10:00",
      "duration_seconds": 737.961708,
      "duration_formatted": "0:12:17",
      "resolution": "1280x720",
      "fps": 30.0,
      "codec": "h264",
      "file_size_mb": 444.9895992279053
    },
    {
      "filename": "KyleMcknight_202511292311_BWL7139063-0.mp4",
      "path": "private-core-barber-cam\\.bwc\\25-41706 Barber, Devon\\KyleMcknight_202511292311_BWL7139063-0.mp4",
      "officer": "KyleMcknight",
      "camera_id": "BWL7139063-0",
      "recording_start": "2025-11-29T23:11:00",
      "duration_seconds": 256.000438,
      "duration_formatted": "0:04:16",
      "resolution": "1920x1080",
      "fps": 30.0,
      "codec": "h264",
      "file_size_mb": 306.70617961883545
    },
    {
      "filename": "NiJonIsom_202511292311_331-0.mp4",
      "path": "private-core-barber-cam\\.bwc\\25-41706 Barber, Devon\\NiJonIsom_202511292311_331-0.mp4",
      "officer": "NiJonIsom",
      "camera_id": "331-0",
      "recording_start": "2025-11-29T23:11:00",
      "duration_seconds": 234.498458,
      "duration_formatted": "0:03:54",
      "resolution": "1280x720",
      "fps": 30.0,
      "codec": "h264",
      "file_size_mb": 141.11518096923828
    },
    {
      "filename": "NiJonIsom_202511292311_331-0.mp4",
      "path": "private-core-barber-cam\\.bwc\\atl-l-003252-25\\officer_Isom\\NiJonIsom_202511292311_331-0.mp4",
      "officer": "NiJonIsom",
      "camera_id": "331-0",
      "recording_start": "2025-11-29T23:11:00",
      "duration_seconds": 234.498458,
      "duration_formatted": "0:03:54",
      "resolution": "1280x720",
      "fps": 30.0,
      "codec": "h264",
      "file_size_mb": 141.11518096923828
    },
    {
      "filename": "KyleMcknight_202511292311_BWL7139063-0.mp4",
      "path": "private-core-barber-cam\\.bwc\\atl-l-003252-25\\officer_Mcknight\\KyleMcknight_202511292311_BWL7139063-0.mp4",
      "officer": "KyleMcknight",
      "camera_id": "BWL7139063-0",
      "recording_start": "2025-11-29T23:11:00",
      "duration_seconds": 256.000438,
      "duration_formatted": "0:04:16",
      "resolution": "1920x1080",
      "fps": 30.0,
      "codec": "h264",
      "file_size_mb": 306.70617961883545
    },
    {
      "filename": "CristianMartin_202511292312_BWL7139081-0.mp4",
      "path": "private-core-barber-cam\\.bwc\\25-41706 Barber, Devon\\CristianMartin_202511292312_BWL7139081-0.mp4",
      "officer": "CristianMartin",
      "camera_id": "BWL7139081-0",
      "recording_start": "2025-11-29T23:12:00",
      "duration_seconds": 134.0,
      "duration_formatted": "0:02:14",
      "resolution": "1920x1080",
      "fps": 30.0,
      "codec": "h264",
      "file_size_mb": 160.56010818481445
    },
    {
      "filename": "NiJonIsom_202511292312_BWL7139126-0.mp4",
      "path": "private-core-barber-cam\\.bwc\\25-41706 Barber, Devon\\NiJonIsom_202511292312_BWL7139126-0.mp4",
      "officer": "NiJonIsom",
      "camera_id": "BWL7139126-0",
      "recording_start": "2025-11-29T23:12:00",
      "duration_seconds": 148.012604,
      "duration_formatted": "0:02:28",
      "resolution": "1920x1080",
      "fps": 30.0,
      "codec": "h264",
      "file_size_mb": 177.3086109161377
    },
    {
      "filename": "NiJonIsom_202511292312_BWL7139126-0.mp4",
      "path": "private-core-barber-cam\\.bwc\\atl-l-003252-25\\officer_Isom\\NiJonIsom_202511292312_BWL7139126-0.mp4",
      "officer": "NiJonIsom",
      "camera_id": "BWL7139126-0",
      "recording_start": "2025-11-29T23:12:00",
      "duration_seconds": 148.012604,
      "duration_formatted": "0:02:28",
      "resolution": "1920x1080",
      "fps": 30.0,
      "codec": "h264",
      "file_size_mb": 177.3086109161377
    },
    {
      "filename": "CristianMartin_202511292312_BWL7139081-0.mp4",
      "path": "private-core-barber-cam\\.bwc\\atl-l-003252-25\\officer_Martin\\CristianMartin_202511292312_BWL7139081-0.mp4",
      "officer": "CristianMartin",
      "camera_id": "BWL7139081-0",
      "recording_start": "2025-11-29T23:12:00",
      "duration_seconds": 134.0,
      "duration_formatted": "0:02:14",
      "resolution": "1920x1080",
      "fps": 30.0,
      "codec": "h264",
      "file_size_mb": 160.56010818481445
    },
    {
      "filename": "CristianMartin_202511292312_BWL7139081-0.mp4",
      "path": "private-core-barber-cam\\_runs\\25-41706-barber-devon\\run_20260103_125038\\video_originals\\25-41706 Barber, Devon\\CristianMartin_202511292312_BWL7139081-0.mp4",
      "officer": "CristianMartin",
      "camera_id": "BWL7139081-0",
      "recording_start": "2025-11-29T23:12:00",
      "duration_seconds": 134.0,
      "duration_formatted": "0:02:14",
      "resolution": "1920x1080",
      "fps": 30.0,
      "codec": "h264",
      "file_size_mb": 160.56010818481445
    },
    {
      "filename": "GaryClune_202511292316_325-0.mp4",
      "path": "private-core-barber-cam\\.bwc\\25-41706 Barber, Devon\\GaryClune_202511292316_325-0.mp4",
      "officer": "GaryClune",
      "camera_id": "325-0",
      "recording_start": "2025-11-29T23:16:00",
      "duration_seconds": 486.992042,
      "duration_formatted": "0:08:06",
      "resolution": "1280x720",
      "fps": 30.0,
      "codec": "h264",
      "file_size_mb": 292.66198539733887
    },
    {
      "filename": "GaryClune_202511292316_325-0.mp4",
      "path": "private-core-barber-cam\\.bwc\\atl-l-003252-25\\sgt_Clune\\GaryClune_202511292316_325-0.mp4",
      "officer": "GaryClune",
      "camera_id": "325-0",
      "recording_start": "2025-11-29T23:16:00",
      "duration_seconds": 486.992042,
      "duration_formatted": "0:08:06",
      "resolution": "1280x720",
      "fps": 30.0,
      "codec": "h264",
      "file_size_mb": 292.66198539733887
    },
    {
      "filename": "GaryClune_202511292317_BWL7139083-0.mp4",
      "path": "private-core-barber-cam\\.bwc\\25-41706 Barber, Devon\\GaryClune_202511292317_BWL7139083-0.mp4",
      "officer": "GaryClune",
      "camera_id": "BWL7139083-0",
      "recording_start": "2025-11-29T23:17:00",
      "duration_seconds": 393.002688,
      "duration_formatted": "0:06:33",
      "resolution": "1920x1080",
      "fps": 30.0,
      "codec": "h264",
      "file_size_mb": 470.88665294647217
    },
    {
      "filename": "GaryClune_202511292317_BWL7139083-0.mp4",
      "path": "private-core-barber-cam\\.bwc\\atl-l-003252-25\\sgt_Clune\\GaryClune_202511292317_BWL7139083-0.mp4",
      "officer": "GaryClune",
      "camera_id": "BWL7139083-0",
      "recording_start": "2025-11-29T23:17:00",
      "duration_seconds": 393.002688,
      "duration_formatted": "0:06:33",
      "resolution": "1920x1080",
      "fps": 30.0,
      "codec": "h264",
      "file_size_mb": 470.88665294647217
    },
    {
      "filename": "EdwardRuiz_202511292318_BWL7139078-0.mp4",
      "path": "private-core-barber-cam\\.bwc\\25-41706 Barber, Devon\\EdwardRuiz_202511292318_BWL7139078-0.mp4",
      "officer": "EdwardRuiz",
      "camera_id": "BWL7139078-0",
      "recording_start": "2025-11-29T23:18:00",
      "duration_seconds": 558.0,
      "duration_formatted": "0:09:18",
      "resolution": "1920x1080",
      "fps": 30.0,
      "codec": "h264",
      "file_size_mb": 668.7532663345337
    },
    {
      "filename": "EdwardRuiz_202511292318_BWL7139078-0.mp4",
      "path": "private-core-barber-cam\\.bwc\\atl-l-003252-25\\officer_Ruiz\\EdwardRuiz_202511292318_BWL7139078-0.mp4",
      "officer": "EdwardRuiz",
      "camera_id": "BWL7139078-0",
      "recording_start": "2025-11-29T23:18:00",
      "duration_seconds": 558.0,
      "duration_formatted": "0:09:18",
      "resolution": "1920x1080",
      "fps": 30.0,
      "codec": "h264",
      "file_size_mb": 668.7532663345337
    },
    {
      "filename": "BryanMerritt_202511292326_BWL7137497-0.mp4",
      "path": "private-core-barber-cam\\.bwc\\25-41706 Barber, Devon\\BryanMerritt_202511292326_BWL7137497-0.mp4",
      "officer": "BryanMerritt",
      "camera_id": "BWL7137497-0",
      "recording_start": "2025-11-29T23:26:00",
      "duration_seconds": 2463.0,
      "duration_formatted": "0:41:03",
      "resolution": "1920x1080",
      "fps": 30.0,
      "codec": "h264",
      "file_size_mb": 2951.365361213684
    },
    {
      "filename": "DennisBakker_202511292326_BWL7137483-0.mp4",
      "path": "private-core-barber-cam\\.bwc\\25-41706 Barber, Devon\\DennisBakker_202511292326_BWL7137483-0.mp4",
      "officer": "DennisBakker",
      "camera_id": "BWL7137483-0",
      "recording_start": "2025-11-29T23:26:00",
      "duration_seconds": 2476.0,
      "duration_formatted": "0:41:16",
      "resolution": "1920x1080",
      "fps": 30.0,
      "codec": "h264",
      "file_size_mb": 2966.7626304626465
    },
    {
      "filename": "BryanMerritt_202511292326_BWL7137497-0.mp4",
      "path": "private-core-barber-cam\\.bwc\\atl-l-003252-25\\officer_Merritt\\BryanMerritt_202511292326_BWL7137497-0.mp4",
      "officer": "BryanMerritt",
      "camera_id": "BWL7137497-0",
      "recording_start": "2025-11-29T23:26:00",
      "duration_seconds": 2463.0,
      "duration_formatted": "0:41:03",
      "resolution": "1920x1080",
      "fps": 30.0,
      "codec": "h264",
      "file_size_mb": 2951.365361213684
    },
    {
      "filename": "DennisBakker_202511292326_BWL7137483-0.mp4",
      "path": "private-core-barber-cam\\.bwc\\atl-l-003252-25\\sgt_Bakker\\DennisBakker_202511292326_BWL7137483-0.mp4",
      "officer": "DennisBakker",
      "camera_id": "BWL7137483-0",
      "recording_start": "2025-11-29T23:26:00",
      "duration_seconds": 2476.0,
      "duration_formatted": "0:41:16",
      "resolution": "1920x1080",
      "fps": 30.0,
      "codec": "h264",
      "file_size_mb": 2966.7626304626465
    },
    {
      "filename": "BryanMerritt_202511292326_BWL7137497-0.mp4",
      "path": "private-core-barber-cam\\_runs\\25-41706-barber-devon\\run_20260103_125038\\video_originals\\25-41706 Barber, Devon\\BryanMerritt_202511292326_BWL7137497-0.mp4",
      "officer": "BryanMerritt",
      "camera_id": "BWL7137497-0",
      "recording_start": "2025-11-29T23:26:00",
      "duration_seconds": 2463.0,
      "duration_formatted": "0:41:03",
      "resolution": "1920x1080",
      "fps": 30.0,
      "codec": "h264",
      "file_size_mb": 2951.365361213684
    },
    {
      "filename": "CristianMartin_202511292328_BWL7139081-0.mp4",
      "path": "private-core-barber-cam\\.bwc\\25-41706 Barber, Devon\\CristianMartin_202511292328_BWL7139081-0.mp4",
      "officer": "CristianMartin",
      "camera_id": "BWL7139081-0",
      "recording_start": "2025-11-29T23:28:00",
      "duration_seconds": 2301.013167,
      "duration_formatted": "0:38:21",
      "resolution": "1920x1080",
      "fps": 30.0,
      "codec": "h264",
      "file_size_mb": 2757.065682411194
    },
    {
      "filename": "NiJonIsom_202511292328_BWL7139126-0.mp4",
      "path": "private-core-barber-cam\\.bwc\\25-41706 Barber, Devon\\NiJonIsom_202511292328_BWL7139126-0.mp4",
      "officer": "NiJonIsom",
      "camera_id": "BWL7139126-0",
      "recording_start": "2025-11-29T23:28:00",
      "duration_seconds": 654.037083,
      "duration_formatted": "0:10:54",
      "resolution": "1920x1080",
      "fps": 30.0,
      "codec": "h264",
      "file_size_mb": 783.6992559432983
    },
    {
      "filename": "NiJonIsom_202511292328_BWL7139126-0.mp4",
      "path": "private-core-barber-cam\\.bwc\\atl-l-003252-25\\officer_Isom\\NiJonIsom_202511292328_BWL7139126-0.mp4",
      "officer": "NiJonIsom",
      "camera_id": "BWL7139126-0",
      "recording_start": "2025-11-29T23:28:00",
      "duration_seconds": 654.037083,
      "duration_formatted": "0:10:54",
      "resolution": "1920x1080",
      "fps": 30.0,
      "codec": "h264",
      "file_size_mb": 783.6992559432983
    },
    {
      "filename": "CristianMartin_202511292328_BWL7139081-0.mp4",
      "path": "private-core-barber-cam\\.bwc\\atl-l-003252-25\\officer_Martin\\CristianMartin_202511292328_BWL7139081-0.mp4",
      "officer": "CristianMartin",
      "camera_id": "BWL7139081-0",
      "recording_start": "2025-11-29T23:28:00",
      "duration_seconds": 2301.013167,
      "duration_formatted": "0:38:21",
      "resolution": "1920x1080",
      "fps": 30.0,
      "codec": "h264",
      "file_size_mb": 2757.065682411194
    },
    {
      "filename": "GaryClune_202511292331_BWL7139083-0.mp4",
      "path": "private-core-barber-cam\\.bwc\\25-41706 Barber, Devon\\GaryClune_202511292331_BWL7139083-0.mp4",
      "officer": "GaryClune",
      "camera_id": "BWL7139083-0",
      "recording_start": "2025-11-29T23:31:00",
      "duration_seconds": 89.004417,
      "duration_formatted": "0:01:29",
      "resolution": "1920x1080",
      "fps": 30.0,
      "codec": "h264",
      "file_size_mb": 106.47554969787598
    },
    {
      "filename": "GaryClune_202511292331_BWL7139083-0.mp4",
      "path": "private-core-barber-cam\\.bwc\\atl-l-003252-25\\sgt_Clune\\GaryClune_202511292331_BWL7139083-0.mp4",
      "officer": "GaryClune",
      "camera_id": "BWL7139083-0",
      "recording_start": "2025-11-29T23:31:00",
      "duration_seconds": 89.004417,
      "duration_formatted": "0:01:29",
      "resolution": "1920x1080",
      "fps": 30.0,
      "codec": "h264",
      "file_size_mb": 106.47554969787598
    },
    {
      "filename": "NiJonIsom_202511292340_BWL7139126-0.mp4",
      "path": "private-core-barber-cam\\.bwc\\25-41706 Barber, Devon\\NiJonIsom_202511292340_BWL7139126-0.mp4",
      "officer": "NiJonIsom",
      "camera_id": "BWL7139126-0",
      "recording_start": "2025-11-29T23:40:00",
      "duration_seconds": 85.034292,
      "duration_formatted": "0:01:25",
      "resolution": "1920x1080",
      "fps": 30.0,
      "codec": "h264",
      "file_size_mb": 101.76931953430176
    },
    {
      "filename": "NiJonIsom_202511292340_BWL7139126-0.mp4",
      "path": "private-core-barber-cam\\.bwc\\atl-l-003252-25\\officer_Isom\\NiJonIsom_202511292340_BWL7139126-0.mp4",
      "officer": "NiJonIsom",
      "camera_id": "BWL7139126-0",
      "recording_start": "2025-11-29T23:40:00",
      "duration_seconds": 85.034292,
      "duration_formatted": "0:01:25",
      "resolution": "1920x1080",
      "fps": 30.0,
      "codec": "h264",
      "file_size_mb": 101.76931953430176
    },
    {
      "filename": "EdwardRuiz_202511292343_312-0.mp4",
      "path": "private-core-barber-cam\\.bwc\\25-41706 Barber, Devon\\EdwardRuiz_202511292343_312-0.mp4",
      "officer": "EdwardRuiz",
      "camera_id": "312-0",
      "recording_start": "2025-11-29T23:43:00",
      "duration_seconds": 3016.517958,
      "duration_formatted": "0:50:16",
      "resolution": "1280x720",
      "fps": 30.0,
      "codec": "h264",
      "file_size_mb": 1816.500168800354
    },
    {
      "filename": "EdwardRuiz_202511292343_312-0.mp4",
      "path": "private-core-barber-cam\\.bwc\\atl-l-003252-25\\officer_Ruiz\\EdwardRuiz_202511292343_312-0.mp4",
      "officer": "EdwardRuiz",
      "camera_id": "312-0",
      "recording_start": "2025-11-29T23:43:00",
      "duration_seconds": 3016.517958,
      "duration_formatted": "0:50:16",
      "resolution": "1280x720",
      "fps": 30.0,
      "codec": "h264",
      "file_size_mb": 1816.500168800354
    },
    {
      "filename": "NiJonIsom_202511292344_BWL7139126-0.mp4",
      "path": "private-core-barber-cam\\.bwc\\25-41706 Barber, Devon\\NiJonIsom_202511292344_BWL7139126-0.mp4",
      "officer": "NiJonIsom",
      "camera_id": "BWL7139126-0",
      "recording_start": "2025-11-29T23:44:00",
      "duration_seconds": 446.036333,
      "duration_formatted": "0:07:26",
      "resolution": "1920x1080",
      "fps": 30.0,
      "codec": "h264",
      "file_size_mb": 534.2905550003052
    },
    {
      "filename": "NiJonIsom_202511292344_BWL7139126-0.mp4",
      "path": "private-core-barber-cam\\.bwc\\atl-l-003252-25\\officer_Isom\\NiJonIsom_202511292344_BWL7139126-0.mp4",
      "officer": "NiJonIsom",
      "camera_id": "BWL7139126-0",
      "recording_start": "2025-11-29T23:44:00",
      "duration_seconds": 446.036333,
      "duration_formatted": "0:07:26",
      "resolution": "1920x1080",
      "fps": 30.0,
      "codec": "h264",
      "file_size_mb": 534.2905550003052
    },
    {
      "filename": "DennisBakker_202511300008_BWL7137483-0.mp4",
      "path": "private-core-barber-cam\\.bwc\\25-41706 Barber, Devon\\DennisBakker_202511300008_BWL7137483-0.mp4",
      "officer": "DennisBakker",
      "camera_id": "BWL7137483-0",
      "recording_start": "2025-11-30T00:08:00",
      "duration_seconds": 86.015979,
      "duration_formatted": "0:01:26",
      "resolution": "1920x1080",
      "fps": 30.0,
      "codec": "h264",
      "file_size_mb": 103.00924587249756
    },
    {
      "filename": "DennisBakker_202511300008_BWL7137483-0.mp4",
      "path": "private-core-barber-cam\\.bwc\\atl-l-003252-25\\sgt_Bakker\\DennisBakker_202511300008_BWL7137483-0.mp4",
      "officer": "DennisBakker",
      "camera_id": "BWL7137483-0",
      "recording_start": "2025-11-30T00:08:00",
      "duration_seconds": 86.015979,
      "duration_formatted": "0:01:26",
      "resolution": "1920x1080",
      "fps": 30.0,
      "codec": "h264",
      "file_size_mb": 103.00924587249756
    },
    {
      "filename": "NiJonIsom_202511300010_331-0.mp4",
      "path": "private-core-barber-cam\\.bwc\\25-41706 Barber, Devon\\NiJonIsom_202511300010_331-0.mp4",
      "officer": "NiJonIsom",
      "camera_id": "331-0",
      "recording_start": "2025-11-30T00:10:00",
      "duration_seconds": 184.023333,
      "duration_formatted": "0:03:04",
      "resolution": "1280x720",
      "fps": 30.0,
      "codec": "h264",
      "file_size_mb": 110.74503517150879
    }
  ],
  "overlap_segments": [
    {
      "start_seconds": 0.0,
      "end_seconds": 6196.517958,
      "duration_seconds": 6196.517958,
      "description": "Recording period"
    }
  ]
}